tritondse/__init__.py
tritondse/arch.py
tritondse/callbacks.py
tritondse/config.py
tritondse/coverage.py
tritondse/exception.py
tritondse/heap_allocator.py
tritondse/logging.py
tritondse/memory.py
tritondse/process_state.py
tritondse/qbdi_trace.py
tritondse/routines.py
tritondse/sanitizers.py
tritondse/seed.py
tritondse/seed_manager.py
tritondse/seed_scheduler.py
tritondse/symbolic_executor.py
tritondse/symbolic_explorator.py
tritondse/thread_context.py
tritondse/trace.py
tritondse/types.py
tritondse/workspace.py
tritondse/loaders/__init__.py
tritondse/loaders/cle_loader.py
tritondse/loaders/loader.py
tritondse/loaders/program.py
tritondse/loaders/quokkaprogram.py
tritondse/probes/__init__.py
tritondse/probes/basic_trace.py
tritondse-0.1.13.dist-info/LICENSE
tritondse-0.1.13.dist-info/METADATA
tritondse-0.1.13.dist-info/WHEEL
tritondse-0.1.13.dist-info/top_level.txt
tritondse-0.1.13.dist-info/RECORD
