Metadata-Version: 2.1
Name: tritondse
Version: 0.1.13
Summary: A library of Dynamic Symbolic Exploration based the Triton library
Home-page: https://github.com/quarkslab/tritondse
Author: Quarkslab
License: Apache License Version 2.0
Project-URL: Documentation, https://quarkslab.github.io/tritondse/
Project-URL: Bug Tracker, https://github.com/quarkslab/tritondse/issues
Project-URL: Source, https://github.com/quarkslab/tritondse
Classifier: Topic :: Security
Classifier: Environment :: Console
Classifier: Operating System :: OS Independent
License-File: LICENSE
Requires-Dist: cle
Requires-Dist: enum-tools
Requires-Dist: lief>=v0.16.0
Requires-Dist: networkx
Requires-Dist: pyQBDI
Requires-Dist: quokka-project
Requires-Dist: triton-library>=1.0.0rc4
